baish/__init__.py
baish/__version__.py
baish/cli.py
baish/config.py
baish/content_processor.py
baish/file_analyzer.py
baish/llm.py
baish/logger.py
baish/main.py
baish/results_manager.py
baish/script_analyzer.py
baish/storage.py
baish/token_counter.py
baish/yara_checker.py
baish/prompts/__init__.py
baish/prompts/security.py
baish/prompts/security_map_reduce.py
baish-0.3.0a1.dist-info/METADATA
baish-0.3.0a1.dist-info/WHEEL
baish-0.3.0a1.dist-info/entry_points.txt
baish-0.3.0a1.dist-info/top_level.txt
baish-0.3.0a1.dist-info/RECORD
