Metadata-Version: 2.2
Name: baish
Version: 0.3.0a1
Summary: A security-focused tool that uses LLMs to analyze shell scripts
Author-email: curtis <curtis@serverascode.com>
License: GPL-3.0
Project-URL: Homepage, https://github.com/taicodotca/baish
Classifier: Development Status :: 3 - Alpha
Classifier: Environment :: Console
Classifier: Intended Audience :: Developers
Classifier: Intended Audience :: System Administrators
Classifier: License :: OSI Approved :: GNU General Public License v3 (GPLv3)
Classifier: Operating System :: POSIX :: Linux
Classifier: Programming Language :: Python :: 3
Classifier: Programming Language :: Python :: 3.10
Classifier: Topic :: Security
Classifier: Topic :: System :: Systems Administration
Classifier: Topic :: Utilities
Requires-Python: >=3.10
Requires-Dist: langchain>=0.3.8
Requires-Dist: anthropic>=0.39.0
Requires-Dist: groq>=0.12.0
Requires-Dist: yara-python>=4.5.1
Requires-Dist: python-magic>=0.4.27
Requires-Dist: pyyaml>=6.0.2
Requires-Dist: rich>=13.9.4
Requires-Dist: langchain-anthropic>=0.3.0
Requires-Dist: langchain-groq>=0.2.1
Requires-Dist: langchain-core>=0.3.21
Requires-Dist: langchain-cohere>=0.3.4
Requires-Dist: cohere>=5.13.6
Requires-Dist: pydantic>=2.10.2
Requires-Dist: loguru>=0.7.2
Requires-Dist: langchain-ollama>=0.2.0
Requires-Dist: ollama>=0.4.2
Requires-Dist: tiktoken>=0.8.0
Requires-Dist: langchain-openai>=0.2.12
Requires-Dist: openai>=1.57.3
